.gitignore
LICENSE.txt
build-deploy.sh
pyproject.toml
readme.md
requirements.txt
setup.cfg
setup.py
configservice/__init__.py
configservice/config.py
configservice.egg-info/PKG-INFO
configservice.egg-info/SOURCES.txt
configservice.egg-info/dependency_links.txt
configservice.egg-info/not-zip-safe
configservice.egg-info/requires.txt
configservice.egg-info/top_level.txt
tests/__init__.py
tests/test_core.py