Metadata-Version: 2.1
Name: configservice
Version: 0.0.17
Summary: A package to help facilitate pulling environmental variables.
Home-page: https://github.com/Cold-Bore-Capital/configuration-service-core
Author: Cold Bore Capital
Author-email: it-group@coldborecapital.com
License: UNKNOWN
Platform: UNKNOWN
Classifier: Programming Language :: Python :: 3.8
Classifier: Topic :: Software Development :: Libraries :: Python Modules
Classifier: Development Status :: 5 - Production/Stable
Requires-Python: >=3.8
License-File: LICENSE.txt
